ls_packers/__init__.py
ls_packers/converters.py
ls_packers/packers.py
ls_packers-0.6.0.dist-info/LICENSE
ls_packers-0.6.0.dist-info/METADATA
ls_packers-0.6.0.dist-info/WHEEL
ls_packers-0.6.0.dist-info/top_level.txt
ls_packers-0.6.0.dist-info/RECORD
