Metadata-Version: 2.1
Name: ls-packers
Version: 0.6.0
Summary: An internal client python API for accessing LightSolver's capabilities
Author-email: Assaf Kalinski <assaf@lightsolver.com>
Project-URL: Homepage, https://lightsolver.com
Classifier: Programming Language :: Python :: 3
Classifier: License :: OSI Approved :: Apache Software License
Classifier: Operating System :: OS Independent
Requires-Python: >=3.8
License-File: LICENSE
Requires-Dist: numpy >=1.21.5
Requires-Dist: msgpack
